{
    "uid": "866702a2-2299-4c21-94cd-cff6f7feb3de",
    "name": "27_RandomForest",
    "preprocessing": [
        {
            "ml_task": "regression",
            "params": {
                "columns_preprocessing": {},
                "target_preprocessing": [
                    "na_exclude"
                ],
                "ml_task": "regression"
            }
        },
        {
            "ml_task": "regression",
            "params": {
                "columns_preprocessing": {},
                "target_preprocessing": [
                    "na_exclude"
                ],
                "ml_task": "regression"
            }
        },
        {
            "ml_task": "regression",
            "params": {
                "columns_preprocessing": {},
                "target_preprocessing": [
                    "na_exclude"
                ],
                "ml_task": "regression"
            }
        },
        {
            "ml_task": "regression",
            "params": {
                "columns_preprocessing": {},
                "target_preprocessing": [
                    "na_exclude"
                ],
                "ml_task": "regression"
            }
        }
    ],
    "learners": [
        {
            "library_version": "1.3.2",
            "algorithm_name": "Random Forest",
            "algorithm_short_name": "Random Forest",
            "uid": "06cf75d2-5260-4ff6-bc91-567926531d58",
            "params": {
                "model_type": "Random Forest",
                "ml_task": "regression",
                "n_jobs": -1,
                "criterion": "squared_error",
                "max_features": 0.9,
                "min_samples_split": 40,
                "max_depth": 4,
                "seed": 3,
                "eval_metric_name": "rmse",
                "explain_level": 1
            },
            "name": "learner_fold_0"
        },
        {
            "library_version": "1.3.2",
            "algorithm_name": "Random Forest",
            "algorithm_short_name": "Random Forest",
            "uid": "bb6741cc-045f-4b82-9373-7a6877ec56bf",
            "params": {
                "model_type": "Random Forest",
                "ml_task": "regression",
                "n_jobs": -1,
                "criterion": "squared_error",
                "max_features": 0.9,
                "min_samples_split": 40,
                "max_depth": 4,
                "seed": 3,
                "eval_metric_name": "rmse",
                "explain_level": 1
            },
            "name": "learner_fold_1"
        },
        {
            "library_version": "1.3.2",
            "algorithm_name": "Random Forest",
            "algorithm_short_name": "Random Forest",
            "uid": "9f7c6036-d213-4787-bacf-a0821cc8e65a",
            "params": {
                "model_type": "Random Forest",
                "ml_task": "regression",
                "n_jobs": -1,
                "criterion": "squared_error",
                "max_features": 0.9,
                "min_samples_split": 40,
                "max_depth": 4,
                "seed": 3,
                "eval_metric_name": "rmse",
                "explain_level": 1
            },
            "name": "learner_fold_2"
        },
        {
            "library_version": "1.3.2",
            "algorithm_name": "Random Forest",
            "algorithm_short_name": "Random Forest",
            "uid": "505aa1d8-2fd3-4d3c-acb6-f933fbc2d91b",
            "params": {
                "model_type": "Random Forest",
                "ml_task": "regression",
                "n_jobs": -1,
                "criterion": "squared_error",
                "max_features": 0.9,
                "min_samples_split": 40,
                "max_depth": 4,
                "seed": 3,
                "eval_metric_name": "rmse",
                "explain_level": 1
            },
            "name": "learner_fold_3"
        }
    ],
    "params": {
        "additional": {
            "trees_in_step": 100,
            "train_cant_improve_limit": 1,
            "min_steps": 1,
            "max_steps": 50,
            "early_stopping_rounds": 50,
            "max_rows_limit": null,
            "max_cols_limit": null
        },
        "preprocessing": {
            "columns_preprocessing": {},
            "target_preprocessing": [
                "na_exclude"
            ],
            "ml_task": "regression"
        },
        "validation_strategy": {
            "validation_type": "kfold",
            "k_folds": 4,
            "shuffle": false,
            "X_path": "automl_results_v2/office_employment_density_cleaned_perform/X.data",
            "y_path": "automl_results_v2/office_employment_density_cleaned_perform/y.data",
            "results_path": "automl_results_v2/office_employment_density_cleaned_perform/"
        },
        "learner": {
            "model_type": "Random Forest",
            "ml_task": "regression",
            "n_jobs": -1,
            "criterion": "squared_error",
            "max_features": 0.9,
            "min_samples_split": 40,
            "max_depth": 4,
            "seed": 3,
            "eval_metric_name": "rmse",
            "explain_level": 1
        },
        "automl_random_state": 1234,
        "ml_task": "regression",
        "explain_level": 1,
        "name": "27_RandomForest",
        "status": "initialized",
        "final_loss": null,
        "train_time": null,
        "data_type": "original",
        "max_time_for_learner": 90.0
    },
    "saved": [
        "27_RandomForest/learner_fold_0.random_forest",
        "27_RandomForest/learner_fold_1.random_forest",
        "27_RandomForest/learner_fold_2.random_forest",
        "27_RandomForest/learner_fold_3.random_forest"
    ],
    "predictions_fname": "27_RandomForest/predictions_out_of_folds.csv",
    "metric_name": "rmse",
    "final_loss": "0.006444735991186118",
    "train_time": 147.03388476371765,
    "is_stacked": false,
    "joblib_version": "1.3.2"
}