{
    "fit_level": "finished",
    "time_controller": {
        "total_time_limit": 3600,
        "model_time_limit": 60,
        "steps": [
            "simple_algorithms",
            "default_algorithms",
            "not_so_random",
            "hill_climbing_1",
            "hill_climbing_2",
            "hill_climbing_3",
            "ensemble",
            "stack",
            "ensemble_stacked"
        ],
        "algorithms": [
            "CatBoost",
            "Xgboost",
            "Random Forest"
        ],
        "spend": [
            {
                "model_name": "prepare_data",
                "model_type": "prepare_data",
                "fit_level": "prepare_data",
                "train_time": 0.47707223892211914
            },
            {
                "model_name": "1_Default_Xgboost",
                "model_type": "Xgboost",
                "fit_level": "default_algorithms",
                "train_time": 162.8568239212036
            },
            {
                "model_name": "2_Default_CatBoost",
                "model_type": "CatBoost",
                "fit_level": "default_algorithms",
                "train_time": 240.34800219535828
            },
            {
                "model_name": "3_Default_RandomForest",
                "model_type": "Random Forest",
                "fit_level": "default_algorithms",
                "train_time": 163.57962894439697
            },
            {
                "model_name": "4_Xgboost",
                "model_type": "Xgboost",
                "fit_level": "not_so_random",
                "train_time": 181.3992509841919
            },
            {
                "model_name": "8_CatBoost",
                "model_type": "CatBoost",
                "fit_level": "not_so_random",
                "train_time": 349.50505018234253
            },
            {
                "model_name": "12_RandomForest",
                "model_type": "Random Forest",
                "fit_level": "not_so_random",
                "train_time": 198.5572853088379
            },
            {
                "model_name": "5_Xgboost",
                "model_type": "Xgboost",
                "fit_level": "not_so_random",
                "train_time": 705.8646447658539
            },
            {
                "model_name": "9_CatBoost",
                "model_type": "CatBoost",
                "fit_level": "not_so_random",
                "train_time": 516.1854839324951
            },
            {
                "model_name": "13_RandomForest",
                "model_type": "Random Forest",
                "fit_level": "not_so_random",
                "train_time": 270.4815480709076
            },
            {
                "model_name": "6_Xgboost",
                "model_type": "Xgboost",
                "fit_level": "not_so_random",
                "train_time": 154.49432802200317
            },
            {
                "model_name": "10_CatBoost",
                "model_type": "CatBoost",
                "fit_level": "not_so_random",
                "train_time": 253.71076083183289
            },
            {
                "model_name": "14_RandomForest",
                "model_type": "Random Forest",
                "fit_level": "not_so_random",
                "train_time": 174.84648489952087
            },
            {
                "model_name": "7_Xgboost",
                "model_type": "Xgboost",
                "fit_level": "not_so_random",
                "train_time": 174.65517592430115
            },
            {
                "model_name": "11_CatBoost",
                "model_type": "CatBoost",
                "fit_level": "not_so_random",
                "train_time": 300.33491706848145
            },
            {
                "model_name": "15_RandomForest",
                "model_type": "Random Forest",
                "fit_level": "not_so_random",
                "train_time": 143.27227687835693
            },
            {
                "model_name": "Ensemble",
                "model_type": "Ensemble",
                "fit_level": "ensemble",
                "train_time": 0.20432591438293457
            }
        ],
        "is_hill_climbing": true,
        "is_stacking": true
    },
    "all_params": {
        "default_algorithms": [
            {
                "additional": {
                    "max_rounds": 10000,
                    "early_stopping_rounds": 50,
                    "max_rows_limit": null,
                    "max_cols_limit": null
                },
                "preprocessing": {
                    "columns_preprocessing": {},
                    "target_preprocessing": [
                        "na_exclude"
                    ],
                    "ml_task": "regression"
                },
                "validation_strategy": {
                    "validation_type": "kfold",
                    "k_folds": 4,
                    "shuffle": false,
                    "X_path": "automl_results_v2/lagged_office_employment_density/X.data",
                    "y_path": "automl_results_v2/lagged_office_employment_density/y.data",
                    "results_path": "automl_results_v2/lagged_office_employment_density/"
                },
                "learner": {
                    "model_type": "Xgboost",
                    "ml_task": "regression",
                    "n_jobs": -1,
                    "objective": "reg:squarederror",
                    "eta": 0.075,
                    "max_depth": 6,
                    "min_child_weight": 1,
                    "subsample": 1.0,
                    "colsample_bytree": 1.0,
                    "seed": 1,
                    "eval_metric": "rmse",
                    "explain_level": 1
                },
                "automl_random_state": 1234,
                "ml_task": "regression",
                "explain_level": 1,
                "name": "1_Default_Xgboost",
                "status": "trained",
                "final_loss": 0.006690914040910423,
                "train_time": 163.20669198036194,
                "data_type": "original",
                "max_time_for_learner": 90.0
            },
            {
                "additional": {
                    "max_rounds": 10000,
                    "early_stopping_rounds": 50,
                    "max_rows_limit": null,
                    "max_cols_limit": null
                },
                "preprocessing": {
                    "columns_preprocessing": {},
                    "target_preprocessing": [
                        "na_exclude"
                    ],
                    "ml_task": "regression"
                },
                "validation_strategy": {
                    "validation_type": "kfold",
                    "k_folds": 4,
                    "shuffle": false,
                    "X_path": "automl_results_v2/lagged_office_employment_density/X.data",
                    "y_path": "automl_results_v2/lagged_office_employment_density/y.data",
                    "results_path": "automl_results_v2/lagged_office_employment_density/"
                },
                "learner": {
                    "model_type": "CatBoost",
                    "ml_task": "regression",
                    "n_jobs": -1,
                    "learning_rate": 0.1,
                    "depth": 6,
                    "rsm": 1,
                    "loss_function": "RMSE",
                    "seed": 2,
                    "eval_metric": "RMSE",
                    "explain_level": 1
                },
                "automl_random_state": 1234,
                "ml_task": "regression",
                "explain_level": 1,
                "name": "2_Default_CatBoost",
                "status": "trained",
                "final_loss": 0.006791323786374925,
                "train_time": 240.6305012702942,
                "data_type": "original",
                "max_time_for_learner": 90.0
            },
            {
                "additional": {
                    "trees_in_step": 100,
                    "train_cant_improve_limit": 1,
                    "min_steps": 1,
                    "max_steps": 50,
                    "early_stopping_rounds": 50,
                    "max_rows_limit": null,
                    "max_cols_limit": null
                },
                "preprocessing": {
                    "columns_preprocessing": {},
                    "target_preprocessing": [
                        "na_exclude"
                    ],
                    "ml_task": "regression"
                },
                "validation_strategy": {
                    "validation_type": "kfold",
                    "k_folds": 4,
                    "shuffle": false,
                    "X_path": "automl_results_v2/lagged_office_employment_density/X.data",
                    "y_path": "automl_results_v2/lagged_office_employment_density/y.data",
                    "results_path": "automl_results_v2/lagged_office_employment_density/"
                },
                "learner": {
                    "model_type": "Random Forest",
                    "ml_task": "regression",
                    "n_jobs": -1,
                    "criterion": "squared_error",
                    "max_features": 0.9,
                    "min_samples_split": 30,
                    "max_depth": 4,
                    "seed": 3,
                    "eval_metric_name": "rmse",
                    "explain_level": 1
                },
                "automl_random_state": 1234,
                "ml_task": "regression",
                "explain_level": 1,
                "name": "3_Default_RandomForest",
                "status": "trained",
                "final_loss": 0.006543732714280655,
                "train_time": 163.8695409297943,
                "data_type": "original",
                "max_time_for_learner": 90.0
            }
        ],
        "not_so_random": [
            {
                "additional": {
                    "max_rounds": 10000,
                    "early_stopping_rounds": 50,
                    "max_rows_limit": null,
                    "max_cols_limit": null
                },
                "preprocessing": {
                    "columns_preprocessing": {},
                    "target_preprocessing": [
                        "na_exclude"
                    ],
                    "ml_task": "regression"
                },
                "validation_strategy": {
                    "validation_type": "kfold",
                    "k_folds": 4,
                    "shuffle": false,
                    "X_path": "automl_results_v2/lagged_office_employment_density/X.data",
                    "y_path": "automl_results_v2/lagged_office_employment_density/y.data",
                    "results_path": "automl_results_v2/lagged_office_employment_density/"
                },
                "learner": {
                    "model_type": "Xgboost",
                    "ml_task": "regression",
                    "n_jobs": -1,
                    "seed": 1235,
                    "objective": "reg:squarederror",
                    "eta": 0.075,
                    "max_depth": 8,
                    "min_child_weight": 5,
                    "subsample": 1.0,
                    "colsample_bytree": 1.0,
                    "eval_metric": "rmse",
                    "explain_level": 1
                },
                "automl_random_state": 1234,
                "ml_task": "regression",
                "explain_level": 1,
                "name": "4_Xgboost",
                "status": "trained",
                "final_loss": 0.006207544774655696,
                "train_time": 181.68248462677002,
                "data_type": "original",
                "max_time_for_learner": 90.0
            },
            {
                "additional": {
                    "max_rounds": 10000,
                    "early_stopping_rounds": 50,
                    "max_rows_limit": null,
                    "max_cols_limit": null
                },
                "preprocessing": {
                    "columns_preprocessing": {},
                    "target_preprocessing": [
                        "na_exclude"
                    ],
                    "ml_task": "regression"
                },
                "validation_strategy": {
                    "validation_type": "kfold",
                    "k_folds": 4,
                    "shuffle": false,
                    "X_path": "automl_results_v2/lagged_office_employment_density/X.data",
                    "y_path": "automl_results_v2/lagged_office_employment_density/y.data",
                    "results_path": "automl_results_v2/lagged_office_employment_density/"
                },
                "learner": {
                    "model_type": "CatBoost",
                    "ml_task": "regression",
                    "n_jobs": -1,
                    "seed": 1235,
                    "learning_rate": 0.05,
                    "depth": 8,
                    "rsm": 0.8,
                    "loss_function": "RMSE",
                    "eval_metric": "RMSE",
                    "explain_level": 1
                },
                "automl_random_state": 1234,
                "ml_task": "regression",
                "explain_level": 1,
                "name": "8_CatBoost",
                "status": "trained",
                "final_loss": 0.007086053274034845,
                "train_time": 349.8657033443451,
                "data_type": "original",
                "max_time_for_learner": 90.0
            },
            {
                "additional": {
                    "trees_in_step": 100,
                    "train_cant_improve_limit": 1,
                    "min_steps": 1,
                    "max_steps": 50,
                    "early_stopping_rounds": 50,
                    "max_rows_limit": null,
                    "max_cols_limit": null
                },
                "preprocessing": {
                    "columns_preprocessing": {},
                    "target_preprocessing": [
                        "na_exclude"
                    ],
                    "ml_task": "regression"
                },
                "validation_strategy": {
                    "validation_type": "kfold",
                    "k_folds": 4,
                    "shuffle": false,
                    "X_path": "automl_results_v2/lagged_office_employment_density/X.data",
                    "y_path": "automl_results_v2/lagged_office_employment_density/y.data",
                    "results_path": "automl_results_v2/lagged_office_employment_density/"
                },
                "learner": {
                    "model_type": "Random Forest",
                    "ml_task": "regression",
                    "n_jobs": -1,
                    "seed": 1235,
                    "criterion": "squared_error",
                    "max_features": 0.5,
                    "min_samples_split": 20,
                    "max_depth": 4,
                    "eval_metric_name": "rmse",
                    "explain_level": 1
                },
                "automl_random_state": 1234,
                "ml_task": "regression",
                "explain_level": 1,
                "name": "12_RandomForest",
                "status": "trained",
                "final_loss": 0.006418586484321269,
                "train_time": 198.8357813358307,
                "data_type": "original",
                "max_time_for_learner": 90.0
            },
            {
                "additional": {
                    "max_rounds": 10000,
                    "early_stopping_rounds": 50,
                    "max_rows_limit": null,
                    "max_cols_limit": null
                },
                "preprocessing": {
                    "columns_preprocessing": {},
                    "target_preprocessing": [
                        "na_exclude"
                    ],
                    "ml_task": "regression"
                },
                "validation_strategy": {
                    "validation_type": "kfold",
                    "k_folds": 4,
                    "shuffle": false,
                    "X_path": "automl_results_v2/lagged_office_employment_density/X.data",
                    "y_path": "automl_results_v2/lagged_office_employment_density/y.data",
                    "results_path": "automl_results_v2/lagged_office_employment_density/"
                },
                "learner": {
                    "model_type": "Xgboost",
                    "ml_task": "regression",
                    "n_jobs": -1,
                    "seed": 1236,
                    "objective": "reg:squarederror",
                    "eta": 0.1,
                    "max_depth": 8,
                    "min_child_weight": 1,
                    "subsample": 1.0,
                    "colsample_bytree": 1.0,
                    "eval_metric": "rmse",
                    "explain_level": 1
                },
                "automl_random_state": 1234,
                "ml_task": "regression",
                "explain_level": 1,
                "name": "5_Xgboost",
                "status": "trained",
                "final_loss": 0.006687490244917317,
                "train_time": 706.1376836299896,
                "data_type": "original",
                "max_time_for_learner": 90.0
            },
            {
                "additional": {
                    "max_rounds": 10000,
                    "early_stopping_rounds": 50,
                    "max_rows_limit": null,
                    "max_cols_limit": null
                },
                "preprocessing": {
                    "columns_preprocessing": {},
                    "target_preprocessing": [
                        "na_exclude"
                    ],
                    "ml_task": "regression"
                },
                "validation_strategy": {
                    "validation_type": "kfold",
                    "k_folds": 4,
                    "shuffle": false,
                    "X_path": "automl_results_v2/lagged_office_employment_density/X.data",
                    "y_path": "automl_results_v2/lagged_office_employment_density/y.data",
                    "results_path": "automl_results_v2/lagged_office_employment_density/"
                },
                "learner": {
                    "model_type": "CatBoost",
                    "ml_task": "regression",
                    "n_jobs": -1,
                    "seed": 1236,
                    "learning_rate": 0.1,
                    "depth": 8,
                    "rsm": 1.0,
                    "loss_function": "MAE",
                    "eval_metric": "RMSE",
                    "explain_level": 1
                },
                "automl_random_state": 1234,
                "ml_task": "regression",
                "explain_level": 1,
                "name": "9_CatBoost",
                "status": "trained",
                "final_loss": 0.006845947234770175,
                "train_time": 516.4781460762024,
                "data_type": "original",
                "max_time_for_learner": 90.0
            },
            {
                "additional": {
                    "trees_in_step": 100,
                    "train_cant_improve_limit": 1,
                    "min_steps": 1,
                    "max_steps": 50,
                    "early_stopping_rounds": 50,
                    "max_rows_limit": null,
                    "max_cols_limit": null
                },
                "preprocessing": {
                    "columns_preprocessing": {},
                    "target_preprocessing": [
                        "na_exclude"
                    ],
                    "ml_task": "regression"
                },
                "validation_strategy": {
                    "validation_type": "kfold",
                    "k_folds": 4,
                    "shuffle": false,
                    "X_path": "automl_results_v2/lagged_office_employment_density/X.data",
                    "y_path": "automl_results_v2/lagged_office_employment_density/y.data",
                    "results_path": "automl_results_v2/lagged_office_employment_density/"
                },
                "learner": {
                    "model_type": "Random Forest",
                    "ml_task": "regression",
                    "n_jobs": -1,
                    "seed": 1236,
                    "criterion": "squared_error",
                    "max_features": 0.7,
                    "min_samples_split": 50,
                    "max_depth": 3,
                    "eval_metric_name": "rmse",
                    "explain_level": 1
                },
                "automl_random_state": 1234,
                "ml_task": "regression",
                "explain_level": 1,
                "name": "13_RandomForest",
                "status": "trained",
                "final_loss": 0.006611856799282578,
                "train_time": 270.7901439666748,
                "data_type": "original",
                "max_time_for_learner": 90.0
            },
            {
                "additional": {
                    "max_rounds": 10000,
                    "early_stopping_rounds": 50,
                    "max_rows_limit": null,
                    "max_cols_limit": null
                },
                "preprocessing": {
                    "columns_preprocessing": {},
                    "target_preprocessing": [
                        "na_exclude"
                    ],
                    "ml_task": "regression"
                },
                "validation_strategy": {
                    "validation_type": "kfold",
                    "k_folds": 4,
                    "shuffle": false,
                    "X_path": "automl_results_v2/lagged_office_employment_density/X.data",
                    "y_path": "automl_results_v2/lagged_office_employment_density/y.data",
                    "results_path": "automl_results_v2/lagged_office_employment_density/"
                },
                "learner": {
                    "model_type": "Xgboost",
                    "ml_task": "regression",
                    "n_jobs": -1,
                    "seed": 1237,
                    "objective": "reg:squarederror",
                    "eta": 0.1,
                    "max_depth": 7,
                    "min_child_weight": 25,
                    "subsample": 0.9,
                    "colsample_bytree": 0.6,
                    "eval_metric": "rmse",
                    "explain_level": 1
                },
                "automl_random_state": 1234,
                "ml_task": "regression",
                "explain_level": 1,
                "name": "6_Xgboost",
                "status": "trained",
                "final_loss": 0.006300966814783105,
                "train_time": 154.80172085762024,
                "data_type": "original",
                "max_time_for_learner": 90.0
            },
            {
                "additional": {
                    "max_rounds": 10000,
                    "early_stopping_rounds": 50,
                    "max_rows_limit": null,
                    "max_cols_limit": null
                },
                "preprocessing": {
                    "columns_preprocessing": {},
                    "target_preprocessing": [
                        "na_exclude"
                    ],
                    "ml_task": "regression"
                },
                "validation_strategy": {
                    "validation_type": "kfold",
                    "k_folds": 4,
                    "shuffle": false,
                    "X_path": "automl_results_v2/lagged_office_employment_density/X.data",
                    "y_path": "automl_results_v2/lagged_office_employment_density/y.data",
                    "results_path": "automl_results_v2/lagged_office_employment_density/"
                },
                "learner": {
                    "model_type": "CatBoost",
                    "ml_task": "regression",
                    "n_jobs": -1,
                    "seed": 1237,
                    "learning_rate": 0.1,
                    "depth": 7,
                    "rsm": 1.0,
                    "loss_function": "RMSE",
                    "eval_metric": "RMSE",
                    "explain_level": 1
                },
                "automl_random_state": 1234,
                "ml_task": "regression",
                "explain_level": 1,
                "name": "10_CatBoost",
                "status": "trained",
                "final_loss": 0.006961588757419867,
                "train_time": 254.13814663887024,
                "data_type": "original",
                "max_time_for_learner": 90.0
            },
            {
                "additional": {
                    "trees_in_step": 100,
                    "train_cant_improve_limit": 1,
                    "min_steps": 1,
                    "max_steps": 50,
                    "early_stopping_rounds": 50,
                    "max_rows_limit": null,
                    "max_cols_limit": null
                },
                "preprocessing": {
                    "columns_preprocessing": {},
                    "target_preprocessing": [
                        "na_exclude"
                    ],
                    "ml_task": "regression"
                },
                "validation_strategy": {
                    "validation_type": "kfold",
                    "k_folds": 4,
                    "shuffle": false,
                    "X_path": "automl_results_v2/lagged_office_employment_density/X.data",
                    "y_path": "automl_results_v2/lagged_office_employment_density/y.data",
                    "results_path": "automl_results_v2/lagged_office_employment_density/"
                },
                "learner": {
                    "model_type": "Random Forest",
                    "ml_task": "regression",
                    "n_jobs": -1,
                    "seed": 1237,
                    "criterion": "squared_error",
                    "max_features": 1.0,
                    "min_samples_split": 40,
                    "max_depth": 6,
                    "eval_metric_name": "rmse",
                    "explain_level": 1
                },
                "automl_random_state": 1234,
                "ml_task": "regression",
                "explain_level": 1,
                "name": "14_RandomForest",
                "status": "trained",
                "final_loss": 0.006696503456057287,
                "train_time": 175.13691067695618,
                "data_type": "original",
                "max_time_for_learner": 90.0
            },
            {
                "additional": {
                    "max_rounds": 10000,
                    "early_stopping_rounds": 50,
                    "max_rows_limit": null,
                    "max_cols_limit": null
                },
                "preprocessing": {
                    "columns_preprocessing": {},
                    "target_preprocessing": [
                        "na_exclude"
                    ],
                    "ml_task": "regression"
                },
                "validation_strategy": {
                    "validation_type": "kfold",
                    "k_folds": 4,
                    "shuffle": false,
                    "X_path": "automl_results_v2/lagged_office_employment_density/X.data",
                    "y_path": "automl_results_v2/lagged_office_employment_density/y.data",
                    "results_path": "automl_results_v2/lagged_office_employment_density/"
                },
                "learner": {
                    "model_type": "Xgboost",
                    "ml_task": "regression",
                    "n_jobs": -1,
                    "seed": 1238,
                    "objective": "reg:squarederror",
                    "eta": 0.15,
                    "max_depth": 8,
                    "min_child_weight": 50,
                    "subsample": 0.6,
                    "colsample_bytree": 0.6,
                    "eval_metric": "rmse",
                    "explain_level": 1
                },
                "automl_random_state": 1234,
                "ml_task": "regression",
                "explain_level": 1,
                "name": "7_Xgboost",
                "status": "trained",
                "final_loss": 0.006569323594703504,
                "train_time": 174.94401788711548,
                "data_type": "original",
                "max_time_for_learner": 90.0
            },
            {
                "additional": {
                    "max_rounds": 10000,
                    "early_stopping_rounds": 50,
                    "max_rows_limit": null,
                    "max_cols_limit": null
                },
                "preprocessing": {
                    "columns_preprocessing": {},
                    "target_preprocessing": [
                        "na_exclude"
                    ],
                    "ml_task": "regression"
                },
                "validation_strategy": {
                    "validation_type": "kfold",
                    "k_folds": 4,
                    "shuffle": false,
                    "X_path": "automl_results_v2/lagged_office_employment_density/X.data",
                    "y_path": "automl_results_v2/lagged_office_employment_density/y.data",
                    "results_path": "automl_results_v2/lagged_office_employment_density/"
                },
                "learner": {
                    "model_type": "CatBoost",
                    "ml_task": "regression",
                    "n_jobs": -1,
                    "seed": 1238,
                    "learning_rate": 0.2,
                    "depth": 8,
                    "rsm": 1.0,
                    "loss_function": "MAE",
                    "eval_metric": "RMSE",
                    "explain_level": 1
                },
                "automl_random_state": 1234,
                "ml_task": "regression",
                "explain_level": 1,
                "name": "11_CatBoost",
                "status": "trained",
                "final_loss": 0.007331507662292324,
                "train_time": 300.6207332611084,
                "data_type": "original",
                "max_time_for_learner": 90.0
            },
            {
                "additional": {
                    "trees_in_step": 100,
                    "train_cant_improve_limit": 1,
                    "min_steps": 1,
                    "max_steps": 50,
                    "early_stopping_rounds": 50,
                    "max_rows_limit": null,
                    "max_cols_limit": null
                },
                "preprocessing": {
                    "columns_preprocessing": {},
                    "target_preprocessing": [
                        "na_exclude"
                    ],
                    "ml_task": "regression"
                },
                "validation_strategy": {
                    "validation_type": "kfold",
                    "k_folds": 4,
                    "shuffle": false,
                    "X_path": "automl_results_v2/lagged_office_employment_density/X.data",
                    "y_path": "automl_results_v2/lagged_office_employment_density/y.data",
                    "results_path": "automl_results_v2/lagged_office_employment_density/"
                },
                "learner": {
                    "model_type": "Random Forest",
                    "ml_task": "regression",
                    "n_jobs": -1,
                    "seed": 1238,
                    "criterion": "squared_error",
                    "max_features": 0.6,
                    "min_samples_split": 50,
                    "max_depth": 6,
                    "eval_metric_name": "rmse",
                    "explain_level": 1
                },
                "automl_random_state": 1234,
                "ml_task": "regression",
                "explain_level": 1,
                "name": "15_RandomForest",
                "status": "trained",
                "final_loss": 0.006580874748752521,
                "train_time": 143.56160068511963,
                "data_type": "original",
                "max_time_for_learner": 90.0
            }
        ],
        "ensemble": [
            {
                "model_type": "ensemble",
                "is_stacked": false,
                "name": "Ensemble",
                "status": "trained",
                "final_loss": 0.006047506896053487,
                "train_time": 0.20432591438293457
            }
        ]
    },
    "adjust_validation": false
}